mcp_semclone/__init__.py
mcp_semclone/server.py
mcp_semclone-1.6.2.dist-info/licenses/AUTHORS.md
mcp_semclone-1.6.2.dist-info/licenses/LICENSE
mcp_semclone-1.6.2.dist-info/METADATA
mcp_semclone-1.6.2.dist-info/WHEEL
mcp_semclone-1.6.2.dist-info/entry_points.txt
mcp_semclone-1.6.2.dist-info/top_level.txt
mcp_semclone-1.6.2.dist-info/RECORD
