Metadata-Version: 2.4
Name: mcp-semclone
Version: 1.6.2
Summary: Model Context Protocol server for SEMCL.ONE OSS compliance toolchain
Author-email: "Oscar Valenzuela B." <oscar.valenzuela.b@gmail.com>
License: Apache-2.0
Project-URL: Homepage, https://github.com/SemClone/mcp-semclone
Project-URL: Bug Reports, https://github.com/SemClone/mcp-semclone/issues
Project-URL: Source, https://github.com/SemClone/mcp-semclone
Keywords: mcp,llm,compliance,license,vulnerability,sbom,sca,oss
Classifier: Development Status :: 4 - Beta
Classifier: Intended Audience :: Developers
Classifier: Topic :: Software Development :: Quality Assurance
Classifier: Topic :: System :: Software Distribution
Classifier: Programming Language :: Python :: 3
Classifier: Programming Language :: Python :: 3.10
Classifier: Programming Language :: Python :: 3.11
Classifier: Programming Language :: Python :: 3.12
Classifier: Programming Language :: Python :: 3.13
Classifier: Operating System :: OS Independent
Classifier: License :: OSI Approved :: Apache Software License
Requires-Python: >=3.10
License-File: LICENSE
License-File: AUTHORS.md
Requires-Dist: mcp>=1.0.0
Requires-Dist: purl2notices>=1.2.7
Requires-Dist: purl2src>=1.2.3
Requires-Dist: ossnotices>=1.0.2
Requires-Dist: binarysniffer>=1.11.3
Requires-Dist: ospac>=1.2.3
Requires-Dist: vulnq>=1.0.2
Requires-Dist: osslili>=1.5.7
Requires-Dist: upmex>=1.6.7
Requires-Dist: aiofiles>=23.0.0
Requires-Dist: pydantic>=2.0.0
Requires-Dist: rich>=13.0.0
Provides-Extra: dev
Requires-Dist: pytest>=7.0.0; extra == "dev"
Requires-Dist: pytest-asyncio>=0.21.0; extra == "dev"
Requires-Dist: black>=23.0.0; extra == "dev"
Requires-Dist: ruff>=0.1.0; extra == "dev"
Requires-Dist: mypy>=1.0.0; extra == "dev"
Dynamic: license-file
